tests/__init__.py
tests/test_atom_number.py
tests/test_drop_each_atom.py
tests/test_drop_each_bond.py
tests/test_plot.py
xymol/__init__.py
xymol/xymol.py
xymol-0.0.1.dist-info/METADATA
xymol-0.0.1.dist-info/WHEEL
xymol-0.0.1.dist-info/top_level.txt
xymol-0.0.1.dist-info/RECORD
