Metadata-Version: 2.1
Name: xymol
Version: 0.0.1
Summary: eXplain Your MOLecule (XYMOL): A Python package to understand and explain atom/bond contributions of small molecules in machine learning models.
Home-page: https://github.com/smu-tao-group/xymol
Author: Hao Tian
Author-email: htian1997@gmail.com
License: Apache License 2.0
Requires-Python: >=3.7
Requires-Dist: rdkit
Requires-Dist: numpy
Requires-Dist: matplotlib
